[
    {
    "id":"Mv01",
    "nombre":"Wall Viki",
    "detalle":"Macrame boho STAR made with ONLY 4 cords",
    "color": "Gray",
    "precio":3500,
    "imagen":"img/macrame01.jpg"},
    {
    "id":"Mv02",
    "nombre":"Wall Jen",
    "detalle":"Light Blue Macramé Wall Hanging with Fringe",
    "color":"Blue",
    "precio":950,
    "imagen":"img/macrame02.jpg"},
    {
    "id":"Mv03",
    "nombre":"Wall Iris",
    "detalle":"Giant Macrame Wall Hangings Radiate Dazzling Rainbow Hues",
    "color":"Multicolored",
    "precio":750,
    "imagen":"img/macrame03.jpg"},
    {
    "id":"Mv04",
    "nombre":"Wall Sandy",
    "detalle":"Neutral Blue/Green Natural Driftwood Macrame Wall Hanging",
    "color":"Green",
    "precio":950,
    "imagen":"img/macrame04.jpg"},
    {
    "id":"Mv05",
    "nombre":"Wall Brisa",
    "detalle":"Leaf Macrame Tapestry Hanging Bohemian Handmade Woven",
    "color":"multicolored",
    "precio":1400,
    "imagen":"img/macrame05.jpg"}
]